errlog_smartgit/__init__.py
errlog_smartgit/cli.py
errlog_smartgit/errlog_smartgit.py
errlog_smartgit/post_install.py
errlog_smartgit/requirements_check.py
pypi_errlog_smartgit-1.5.0.dist-info/licenses/LICENSE
pypi_errlog_smartgit-1.5.0.dist-info/METADATA
pypi_errlog_smartgit-1.5.0.dist-info/WHEEL
pypi_errlog_smartgit-1.5.0.dist-info/entry_points.txt
pypi_errlog_smartgit-1.5.0.dist-info/top_level.txt
pypi_errlog_smartgit-1.5.0.dist-info/RECORD
