Metadata-Version: 2.4
Name: pypi-errlog-smartgit
Version: 1.5.0
Summary: errlog-smartgit - SmartGit Error Handler with detailed feedback
Home-page: https://github.com/abucodingai/errlog-smartgit-py
Author: Abu Shariff
Author-email: abu.shariffaiml@gmail.com
Project-URL: GitHub CLI, https://cli.github.com
Project-URL: Documentation, https://github.com/abucodingai/errlog-smartgit-py
Classifier: Programming Language :: Python :: 3
Classifier: Programming Language :: Python :: 3.8
Classifier: Programming Language :: Python :: 3.9
Classifier: Programming Language :: Python :: 3.10
Classifier: Programming Language :: Python :: 3.11
Classifier: License :: OSI Approved :: MIT License
Classifier: Operating System :: OS Independent
Classifier: Development Status :: 5 - Production/Stable
Classifier: Intended Audience :: Developers
Classifier: Topic :: Software Development :: Version Control :: Git
Requires-Python: >=3.8
License-File: LICENSE
Requires-Dist: pypi-smartgit>=1.0.0
Requires-Dist: colorama>=0.4.4
Provides-Extra: dev
Requires-Dist: pytest>=7.0; extra == "dev"
Requires-Dist: black>=22.0; extra == "dev"
Requires-Dist: flake8>=4.0; extra == "dev"
Dynamic: author
Dynamic: author-email
Dynamic: classifier
Dynamic: description
Dynamic: description-content-type
Dynamic: home-page
Dynamic: license-file
Dynamic: project-url
Dynamic: provides-extra
Dynamic: requires-dist
Dynamic: requires-python
Dynamic: summary
